[
  {
    "Input": "15'inde döneceğim",
    "Context": {
      "ReferenceDateTime": "2016-11-07T00:00:00"
    },
    "NotSupportedByDesign": "javascript,python,java",
    "Results": [
      {
        "Text": "15",
        "Type": "date",
        "Value": {
          "Timex": "XXXX-XX-15",
          "FutureResolution": {
            "date": "2016-11-15"
          },
          "PastResolution": {
            "date": "2016-10-15"
          }
        },
        "Start": 0,
        "Length": 2
      }
    ]
  },
  {
    "Input": "2 Ekim'de döneceğim",
    "Context": {
      "ReferenceDateTime": "2016-11-07T00:00:00"
    },
    "NotSupportedByDesign": "javascript,python,java",
    "Results": [
      {
        "Text": "2 Ekim",
        "Type": "date",
        "Value": {
          "Timex": "XXXX-10-02",
          "FutureResolution": {
            "date": "2017-10-02"
          },
          "PastResolution": {
            "date": "2016-10-02"
          }
        },
        "Start": 0,
        "Length": 6
      }
    ]
  },
  {
    "Input": "12 Ocak 2016'da döneceğim",
    "Context": {
      "ReferenceDateTime": "2016-11-07T00:00:00"
    },
    "NotSupportedByDesign": "javascript,python,java",
    "Results": [
      {
        "Text": "12 Ocak 2016",
        "Type": "date",
        "Value": {
          "Timex": "2016-01-12",
          "FutureResolution": {
            "date": "2016-01-12"
          },
          "PastResolution": {
            "date": "2016-01-12"
          }
        },
        "Start": 0,
        "Length": 12
      }
    ]
  },
  {
    "Input": "12 Ocak 2016 Pazartesi döneceğim",
    "Context": {
      "ReferenceDateTime": "2016-11-07T00:00:00"
    },
    "NotSupportedByDesign": "javascript,python,java",
    "Results": [
      {
        "Text": "12 Ocak 2016 Pazartesi",
        "Type": "date",
        "Value": {
          "Timex": "2016-01-12",
          "FutureResolution": {
            "date": "2016-01-12"
          },
          "PastResolution": {
            "date": "2016-01-12"
          }
        },
        "Start": 0,
        "Length": 22
      }
    ]
  },
  {
    "Input": "22/02/2016'da döneceğim",
    "Context": {
      "ReferenceDateTime": "2016-11-07T00:00:00"
    },
    "NotSupportedByDesign": "javascript,python,java",
    "Results": [
      {
        "Text": "22/02/2016",
        "Type": "date",
        "Value": {
          "Timex": "2016-02-22",
          "FutureResolution": {
            "date": "2016-02-22"
          },
          "PastResolution": {
            "date": "2016-02-22"
          }
        },
        "Start": 0,
        "Length": 10
      }
    ]
  },
  {
    "Input": "21/04/2016'da döneceğim",
    "Context": {
      "ReferenceDateTime": "2016-11-07T00:00:00"
    },
    "NotSupportedByDesign": "javascript,python,java",
    "Results": [
      {
        "Text": "21/04/2016",
        "Type": "date",
        "Value": {
          "Timex": "2016-04-21",
          "FutureResolution": {
            "date": "2016-04-21"
          },
          "PastResolution": {
            "date": "2016-04-21"
          }
        },
        "Start": 0,
        "Length": 10
      }
    ]
  },
  {
    "Input": "21-04-2016'da döneceğim",
    "Context": {
      "ReferenceDateTime": "2016-11-07T00:00:00"
    },
    "NotSupportedByDesign": "javascript,python,java",
    "Results": [
      {
        "Text": "21-04-2016",
        "Type": "date",
        "Value": {
          "Timex": "2016-04-21",
          "FutureResolution": {
            "date": "2016-04-21"
          },
          "PastResolution": {
            "date": "2016-04-21"
          }
        },
        "Start": 0,
        "Length": 10
      }
    ]
  },
  {
    "Input": "12/08/2015'te döneceğim",
    "Context": {
      "ReferenceDateTime": "2016-11-07T00:00:00"
    },
    "NotSupportedByDesign": "javascript,python,java",
    "Results": [
      {
        "Text": "12/08/2015",
        "Type": "date",
        "Value": {
          "Timex": "2015-08-12",
          "FutureResolution": {
            "date": "2015-08-12"
          },
          "PastResolution": {
            "date": "2015-08-12"
          }
        },
        "Start": 0,
        "Length": 10
      }
    ]
  },
  {
    "Input": "1 Ocak'ta döneceğim",
    "Context": {
      "ReferenceDateTime": "2016-11-07T00:00:00"
    },
    "NotSupportedByDesign": "javascript,python,java",
    "Results": [
      {
        "Text": "1 Ocak",
        "Type": "date",
        "Value": {
          "Timex": "XXXX-01-01",
          "FutureResolution": {
            "date": "2017-01-01"
          },
          "PastResolution": {
            "date": "2016-01-01"
          }
        },
        "Start": 0,
        "Length": 6
      }
    ]
  },
  {
    "Input": "22 Ocak Çarşamba döneceğim",
    "Context": {
      "ReferenceDateTime": "2016-11-07T00:00:00"
    },
    "NotSupportedByDesign": "javascript,python,java",
    "Results": [
      {
        "Text": "22 Ocak Çarşamba",
        "Type": "date",
        "Value": {
          "Timex": "XXXX-01-22",
          "FutureResolution": {
            "date": "2017-01-22"
          },
          "PastResolution": {
            "date": "2016-01-22"
          }
        },
        "Start": 0,
        "Length": 16
      }
    ]
  },
  {
    "Input": "Yirmi bir Mayıs'ta döneceğim",
    "Context": {
      "ReferenceDateTime": "2016-11-07T00:00:00"
    },
    "NotSupportedByDesign": "javascript,python,java",
    "Results": [
      {
        "Text": "Yirmi bir Mayıs",
        "Type": "date",
        "Value": {
          "Timex": "XXXX-05-21",
          "FutureResolution": {
            "date": "2017-05-21"
          },
          "PastResolution": {
            "date": "2016-05-21"
          }
        },
        "Start": 0,
        "Length": 15
      }
    ]
  },
  {
    "Input": "Ağustos'un ikisinde döneceğim",
    "Context": {
      "ReferenceDateTime": "2016-11-07T00:00:00"
    },
    "NotSupportedByDesign": "javascript,python,java",
    "Results": [
      {
        "Text": "Ağustos'un ikisi",
        "Type": "date",
        "Value": {
          "Timex": "XXXX-08-02",
          "FutureResolution": {
            "date": "2017-08-02"
          },
          "PastResolution": {
            "date": "2016-08-02"
          }
        },
        "Start": 0,
        "Length": 16
      }
    ]
  },
  {
    "Input": "Haziran'ın yirmi ikisinde döneceğim",
    "Context": {
      "ReferenceDateTime": "2016-11-07T00:00:00"
    },
    "NotSupportedByDesign": "javascript,python,java",
    "Results": [
      {
        "Text": "Haziran'ın yirmi ikisi",
        "Type": "date",
        "Value": {
          "Timex": "XXXX-06-22",
          "FutureResolution": {
            "date": "2017-06-22"
          },
          "PastResolution": {
            "date": "2016-06-22"
          }
        },
        "Start": 0,
        "Length": 22
      }
    ]
  },
  {
    "Input": "Cuma günü döneceğim",
    "Context": {
      "ReferenceDateTime": "2016-11-07T00:00:00"
    },
    "NotSupportedByDesign": "javascript,python,java",
    "Results": [
      {
        "Text": "Cuma",
        "Type": "date",
        "Value": {
          "Timex": "XXXX-WXX-5",
          "FutureResolution": {
            "date": "2016-11-11"
          },
          "PastResolution": {
            "date": "2016-11-04"
          }
        },
        "Start": 0,
        "Length": 4
      }
    ]
  },
  {
    "Input": "Bugün döneceğim",
    "Context": {
      "ReferenceDateTime": "2016-11-07T00:00:00"
    },
    "NotSupportedByDesign": "javascript,python,java",
    "Results": [
      {
        "Text": "Bugün",
        "Type": "date",
        "Value": {
          "Timex": "2016-11-07",
          "FutureResolution": {
            "date": "2016-11-07"
          },
          "PastResolution": {
            "date": "2016-11-07"
          }
        },
        "Start": 0,
        "Length": 5
      }
    ]
  },
  {
    "Input": "Yarın döneceğim",
    "Context": {
      "ReferenceDateTime": "2016-11-07T00:00:00"
    },
    "NotSupportedByDesign": "javascript,python,java",
    "Results": [
      {
        "Text": "yarın",
        "Type": "date",
        "Value": {
          "Timex": "2016-11-08",
          "FutureResolution": {
            "date": "2016-11-08"
          },
          "PastResolution": {
            "date": "2016-11-08"
          }
        },
        "Start": 0,
        "Length": 5
      }
    ]
  },
  {
    "Input": "Dün döneceğim",
    "Context": {
      "ReferenceDateTime": "2016-11-07T00:00:00"
    },
    "NotSupportedByDesign": "javascript,python,java",
    "Results": [
      {
        "Text": "dün",
        "Type": "date",
        "Value": {
          "Timex": "2016-11-06",
          "FutureResolution": {
            "date": "2016-11-06"
          },
          "PastResolution": {
            "date": "2016-11-06"
          }
        },
        "Start": 0,
        "Length": 3
      }
    ]
  },
  {
    "Input": "Dünden önceki gün döneceğim",
    "Context": {
      "ReferenceDateTime": "2016-11-07T00:00:00"
    },
    "NotSupportedByDesign": "javascript,python,java",
    "Results": [
      {
        "Text": "dünden önceki gün",
        "Type": "date",
        "Value": {
          "Timex": "2016-11-05",
          "FutureResolution": {
            "date": "2016-11-05"
          },
          "PastResolution": {
            "date": "2016-11-05"
          }
        },
        "Start": 0,
        "Length": 17
      }
    ]
  },
  {
    "Input": "yarından sonraki gün döneceğim",
    "Context": {
      "ReferenceDateTime": "2016-11-07T00:00:00"
    },
    "NotSupportedByDesign": "javascript,python,java",
    "Results": [
      {
        "Text": "yarından sonraki gün",
        "Type": "date",
        "Value": {
          "Timex": "2016-11-09",
          "FutureResolution": {
            "date": "2016-11-09"
          },
          "PastResolution": {
            "date": "2016-11-09"
          }
        },
        "Start": 0,
        "Length": 20
      }
    ]
  },
  {
    "Input": "Ertesi gün döneceğim",
    "Context": {
      "ReferenceDateTime": "2016-11-07T00:00:00"
    },
    "NotSupportedByDesign": "javascript,python,java",
    "Results": [
      {
        "Text": "ertesi gün",
        "Type": "date",
        "Value": {
          "Timex": "2016-11-08",
          "FutureResolution": {
            "date": "2016-11-08"
          },
          "PastResolution": {
            "date": "2016-11-08"
          }
        },
        "Start": 0,
        "Length": 10
      }
    ]
  },
  {
    "Input": "Bu Cuma döneceğim",
    "Context": {
      "ReferenceDateTime": "2016-11-07T00:00:00"
    },
    "NotSupportedByDesign": "javascript,python,java",
    "Results": [
      {
        "Text": "bu Cuma",
        "Type": "date",
        "Value": {
          "Timex": "2016-11-11",
          "FutureResolution": {
            "date": "2016-11-11"
          },
          "PastResolution": {
            "date": "2016-11-11"
          }
        },
        "Start": 0,
        "Length": 7
      }
    ]
  },
  {
    "Input": "Gelecek Pazar döneceğim",
    "Context": {
      "ReferenceDateTime": "2016-11-07T00:00:00"
    },
    "NotSupportedByDesign": "javascript,python,java",
    "Results": [
      {
        "Text": "gelecek Pazar",
        "Type": "date",
        "Value": {
          "Timex": "2016-11-20",
          "FutureResolution": {
            "date": "2016-11-20"
          },
          "PastResolution": {
            "date": "2016-11-20"
          }
        },
        "Start": 0,
        "Length": 13
      }
    ]
  },
  {
    "Input": "geçen Pazar döneceğim",
    "Context": {
      "ReferenceDateTime": "2016-11-07T00:00:00"
    },
    "NotSupportedByDesign": "javascript,python,java",
    "Results": [
      {
        "Text": "geçen Pazar",
        "Type": "date",
        "Value": {
          "Timex": "2016-11-06",
          "FutureResolution": {
            "date": "2016-11-06"
          },
          "PastResolution": {
            "date": "2016-11-06"
          }
        },
        "Start": 0,
        "Length": 11
      }
    ]
  },
  {
    "Input": "Bu hafta Cuma döneceğim",
    "Context": {
      "ReferenceDateTime": "2016-11-07T00:00:00"
    },
    "NotSupportedByDesign": "javascript,python,java",
    "Results": [
      {
        "Text": "bu hafta Cuma",
        "Type": "date",
        "Value": {
          "Timex": "2016-11-11",
          "FutureResolution": {
            "date": "2016-11-11"
          },
          "PastResolution": {
            "date": "2016-11-11"
          }
        },
        "Start": 0,
        "Length": 13
      }
    ]
  },
  {
    "Input": "Gelecek hafta Pazar döneceğim",
    "Context": {
      "ReferenceDateTime": "2016-11-07T00:00:00"
    },
    "NotSupportedByDesign": "javascript,python,java",
    "Results": [
      {
        "Text": "Gelecek hafta Pazar",
        "Type": "date",
        "Value": {
          "Timex": "2016-11-20",
          "FutureResolution": {
            "date": "2016-11-20"
          },
          "PastResolution": {
            "date": "2016-11-20"
          }
        },
        "Start": 0,
        "Length": 19
      }
    ]
  },
  {
    "Input": "Geçen hafta Pazar döneceğim",
    "Context": {
      "ReferenceDateTime": "2016-11-07T00:00:00"
    },
    "NotSupportedByDesign": "javascript,python,java",
    "Results": [
      {
        "Text": "Geçen hafta Pazar",
        "Type": "date",
        "Value": {
          "Timex": "2016-11-06",
          "FutureResolution": {
            "date": "2016-11-06"
          },
          "PastResolution": {
            "date": "2016-11-06"
          }
        },
        "Start": 0,
        "Length": 17
      }
    ]
  },
  {
    "Input": "Geçen gün döneceğim",
    "Context": {
      "ReferenceDateTime": "2016-11-07T00:00:00"
    },
    "NotSupportedByDesign": "javascript,python,java",
    "Results": [
      {
        "Text": "geçen gün",
        "Type": "date",
        "Value": {
          "Timex": "2016-11-06",
          "FutureResolution": {
            "date": "2016-11-06"
          },
          "PastResolution": {
            "date": "2016-11-06"
          }
        },
        "Start": 0,
        "Length": 9
      }
    ]
  },
  {
    "Input": "Son gün döneceğim",
    "Context": {
      "ReferenceDateTime": "2016-11-07T00:00:00"
    },
    "NotSupportedByDesign": "javascript,python,java",
    "Results": [
      {
        "Text": "son gün",
        "Type": "date",
        "Value": {
          "Timex": "2016-11-06",
          "FutureResolution": {
            "date": "2016-11-06"
          },
          "PastResolution": {
            "date": "2016-11-06"
          }
        },
        "Start": 0,
        "Length": 7
      }
    ]
  },
  {
    "Input": "O gün döneceğim",
    "Context": {
      "ReferenceDateTime": "2016-11-07T00:00:00"
    },
    "NotSupportedByDesign": "javascript,python,java",
    "Results": [
      {
        "Text": "O gün",
        "Type": "date",
        "Value": {
          "Timex": "2016-11-07",
          "FutureResolution": {
            "date": "2016-11-07"
          },
          "PastResolution": {
            "date": "2016-11-07"
          }
        },
        "Start": 0,
        "Length": 5
      }
    ]
  },
  {
    "Input": "15 Haziran 2016'da döneceğim",
    "Context": {
      "ReferenceDateTime": "2016-11-07T00:00:00"
    },
    "NotSupportedByDesign": "javascript,python,java",
    "Results": [
      {
        "Text": "15 Haziran 2016",
        "Type": "date",
        "Value": {
          "Timex": "2016-06-15",
          "FutureResolution": {
            "date": "2016-06-15"
          },
          "PastResolution": {
            "date": "2016-06-15"
          }
        },
        "Start": 0,
        "Length": 15
      }
    ]
  },
  {
    "Input": "Temmuz'un ilk Cuma günü döneceğim",
    "Context": {
      "ReferenceDateTime": "2016-11-07T00:00:00"
    },
    "NotSupportedByDesign": "javascript,python,java",
    "Results": [
      {
        "Text": "Temmuz'un ilk Cuma günü",
        "Type": "date",
        "Value": {
          "Timex": "XXXX-07-WXX-5-#1",
          "FutureResolution": {
            "date": "2017-07-07"
          },
          "PastResolution": {
            "date": "2016-07-01"
          }
        },
        "Start": 0,
        "Length": 23
      }
    ]
  },
  {
    "Input": "Bu ayın ilk Cuma günü döneceğim",
    "Context": {
      "ReferenceDateTime": "2016-11-07T00:00:00"
    },
    "NotSupportedByDesign": "javascript,python,java",
    "Results": [
      {
        "Text": "Bu ayın ilk Cuma günü",
        "Type": "date",
        "Value": {
          "Timex": "XXXX-11-WXX-5-#1",
          "FutureResolution": {
            "date": "2016-11-04"
          },
          "PastResolution": {
            "date": "2016-11-04"
          }
        },
        "Start": 0,
        "Length": 21
      }
    ]
  },
  {
    "Input": "Gelecek hafta Cuma günü döneceğim",
    "Context": {
      "ReferenceDateTime": "2016-11-07T00:00:00"
    },
    "NotSupportedByDesign": "javascript,python,java",
    "Results": [
      {
        "Text": "Gelecek hafta Cuma günü",
        "Type": "date",
        "Value": {
          "Timex": "2016-11-18",
          "FutureResolution": {
            "date": "2016-11-18"
          },
          "PastResolution": {
            "date": "2016-11-18"
          }
        },
        "Start": 0,
        "Length": 23
      }
    ]
  },
  {
    "Input": "Benim günüm neye benziyor?",
    "Context": {
      "ReferenceDateTime": "2016-11-07T00:00:00"
    },
    "NotSupportedByDesign": "javascript,python,java",
    "Results": [
      {
        "Text": "benim günüm",
        "Type": "date",
        "Value": {
          "Timex": "2016-11-07",
          "FutureResolution": {
            "date": "2016-11-07"
          },
          "PastResolution": {
            "date": "2016-11-07"
          }
        },
        "Start": 0,
        "Length": 11
      }
    ]
  },
  {
    "Input": "iki hafta içinde döneceğim",
    "Context": {
      "ReferenceDateTime": "2016-11-07T00:00:00"
    },
    "NotSupportedByDesign": "javascript,python,java",
    "Results": [
      {
        "Text": "iki hafta içinde",
        "Type": "date",
        "Value": {
          "Timex": "2016-11-21",
          "FutureResolution": {
            "date": "2016-11-21"
          },
          "PastResolution": {
            "date": "2016-11-21"
          }
        },
        "Start": 0,
        "Length": 16
      }
    ]
  },
  {
    "Input": "Bir ay önce kime mail attım",
    "Context": {
      "ReferenceDateTime": "2016-11-07T00:00:00"
    },
    "NotSupportedByDesign": "javascript,python,java",
    "Results": [
      {
        "Text": "bir ay önce",
        "Type": "date",
        "Value": {
          "Timex": "2016-10-07",
          "FutureResolution": {
            "date": "2016-10-07"
          },
          "PastResolution": {
            "date": "2016-10-07"
          }
        },
        "Start": 0,
        "Length": 11
      }
    ]
  },
  {
    "Input": "birkaç ay önce kime mail attım",
    "Context": {
      "ReferenceDateTime": "2016-11-07T00:00:00"
    },
    "NotSupportedByDesign": "javascript,python,java",
    "Results": [
      {
        "Text": "birkaç ay önce",
        "Type": "date",
        "Value": {
          "Timex": "2016-08-07",
          "FutureResolution": {
            "date": "2016-08-07"
          },
          "PastResolution": {
            "date": "2016-08-07"
          }
        },
        "Start": 0,
        "Length": 14
      }
    ]
  },
  {
    "Input": "birkaç gün önce kime mail attım",
    "Context": {
      "ReferenceDateTime": "2016-11-07T00:00:00"
    },
    "NotSupportedByDesign": "javascript,python,java",
    "Results": [
      {
        "Text": "birkaç gün önce",
        "Type": "date",
        "Value": {
          "Timex": "2016-11-04",
          "FutureResolution": {
            "date": "2016-11-04"
          },
          "PastResolution": {
            "date": "2016-11-04"
          }
        },
        "Start": 0,
        "Length": 15
      }
    ]
  },
  {
    "Input": "27'sinde döndüm",
    "Context": {
      "ReferenceDateTime": "2016-11-07T00:00:00"
    },
    "NotSupportedByDesign": "javascript,python,java",
    "Results": [
      {
        "Text": "27",
        "Type": "date",
        "Value": {
          "Timex": "XXXX-XX-27",
          "FutureResolution": {
            "date": "2016-11-27"
          },
          "PastResolution": {
            "date": "2016-10-27"
          }
        },
        "Start": 0,
        "Length": 2
      }
    ]
  },
  {
    "Input": "21'inde döndüm",
    "Context": {
      "ReferenceDateTime": "2016-11-07T00:00:00"
    },
    "NotSupportedByDesign": "javascript,python,java",
    "Results": [
      {
        "Text": "21",
        "Type": "date",
        "Value": {
          "Timex": "XXXX-XX-21",
          "FutureResolution": {
            "date": "2016-11-21"
          },
          "PastResolution": {
            "date": "2016-10-21"
          }
        },
        "Start": 0,
        "Length": 2
      }
    ]
  },
  {
    "Input": "22'sinde döndüm",
    "Context": {
      "ReferenceDateTime": "2016-11-07T00:00:00"
    },
    "NotSupportedByDesign": "javascript,python,java",
    "Results": [
      {
        "Text": "22",
        "Type": "date",
        "Value": {
          "Timex": "XXXX-XX-22",
          "FutureResolution": {
            "date": "2016-11-22"
          },
          "PastResolution": {
            "date": "2016-10-22"
          }
        },
        "Start": 0,
        "Length": 2
      }
    ]
  },
  {
    "Input": "yirmi ikisinde döndüm",
    "Context": {
      "ReferenceDateTime": "2016-11-07T00:00:00"
    },
    "NotSupportedByDesign": "javascript,python,java",
    "Results": [
      {
        "Text": "yirmi ikisi",
        "Type": "date",
        "Value": {
          "Timex": "XXXX-XX-22",
          "FutureResolution": {
            "date": "2016-11-22"
          },
          "PastResolution": {
            "date": "2016-10-22"
          }
        },
        "Start": 0,
        "Length": 11
      }
    ]
  },
  {
    "Input": "otuzunda döndüm",
    "Context": {
      "ReferenceDateTime": "2016-11-07T00:00:00"
    },
    "NotSupportedByDesign": "javascript,python,java",
    "Results": [
      {
        "Text": "otuzu",
        "Type": "date",
        "Value": {
          "Timex": "XXXX-XX-30",
          "FutureResolution": {
            "date": "2016-11-30"
          },
          "PastResolution": {
            "date": "2016-10-30"
          }
        },
        "Start": 0,
        "Length": 5
      }
    ]
  },
  {
    "Input": "Perşembe 21'inde döndüm",
    "Context": {
      "ReferenceDateTime": "2017-09-27T00:00:00"
    },
    "NotSupportedByDesign": "javascript,python,java",
    "Results": [
      {
        "Text": "Perşembe 21'i",
        "Type": "date",
        "Value": {
          "Timex": "2017-09-21",
          "FutureResolution": {
            "date": "2017-09-21"
          },
          "PastResolution": {
            "date": "2017-09-21"
          }
        },
        "Start": 0,
        "Length": 13
      }
    ]
  },
  {
    "Input": "Cuma 22'sinde döndüm",
    "Context": {
      "ReferenceDateTime": "2017-09-27T00:00:00"
    },
    "NotSupportedByDesign": "javascript,python,java",
    "Results": [
      {
        "Text": "Cuma 22'si",
        "Type": "date",
        "Value": {
          "Timex": "2017-09-22",
          "FutureResolution": {
            "date": "2017-09-22"
          },
          "PastResolution": {
            "date": "2017-09-22"
          }
        },
        "Start": 0,
        "Length": 10
      }
    ]
  },
  {
    "Input": "Cumartesi 23'ünde döndüm",
    "Context": {
      "ReferenceDateTime": "2017-09-27T00:00:00"
    },
    "NotSupportedByDesign": "javascript,python,java",
    "Results": [
      {
        "Text": "Cumartesi 23'ü",
        "Type": "date",
        "Value": {
          "Timex": "2017-09-23",
          "FutureResolution": {
            "date": "2017-09-23"
          },
          "PastResolution": {
            "date": "2017-09-23"
          }
        },
        "Start": 0,
        "Length": 14
      }
    ]
  },
  {
    "Input": "Cuma 15'inde döndüm",
    "Context": {
      "ReferenceDateTime": "2017-09-27T00:00:00"
    },
    "NotSupportedByDesign": "javascript,python,java",
    "Results": [
      {
        "Text": "Cuma 15'i",
        "Type": "date",
        "Value": {
          "Timex": "2017-09-15",
          "FutureResolution": {
            "date": "2017-09-15"
          },
          "PastResolution": {
            "date": "2017-09-15"
          }
        },
        "Start": 0,
        "Length": 9
      }
    ]
  },
  {
    "Input": "Perşembe yirmi birinde döndüm",
    "Context": {
      "ReferenceDateTime": "2017-09-27T00:00:00"
    },
    "NotSupportedByDesign": "javascript,python,java",
    "Results": [
      {
        "Text": "Perşembe yirmi biri",
        "Type": "date",
        "Value": {
          "Timex": "2017-09-21",
          "FutureResolution": {
            "date": "2017-09-21"
          },
          "PastResolution": {
            "date": "2017-09-21"
          }
        },
        "Start": 0,
        "Length": 19
      }
    ]
  },
  {
    "Input": "Cuma yirmi ikisinde döndüm",
    "Context": {
      "ReferenceDateTime": "2017-09-27T00:00:00"
    },
    "NotSupportedByDesign": "javascript,python,java",
    "Results": [
      {
        "Text": "Cuma yirmi ikisi",
        "Type": "date",
        "Value": {
          "Timex": "2017-09-22",
          "FutureResolution": {
            "date": "2017-09-22"
          },
          "PastResolution": {
            "date": "2017-09-22"
          }
        },
        "Start": 0,
        "Length": 16
      }
    ]
  },
  {
    "Input": "Cuma on beşinde döndüm",
    "Context": {
      "ReferenceDateTime": "2017-09-27T00:00:00"
    },
    "NotSupportedByDesign": "javascript,python,java",
    "Results": [
      {
        "Text": "Cuma on beşi",
        "Type": "date",
        "Value": {
          "Timex": "2017-09-15",
          "FutureResolution": {
            "date": "2017-09-15"
          },
          "PastResolution": {
            "date": "2017-09-15"
          }
        },
        "Start": 0,
        "Length": 12
      }
    ]
  },
  {
    "Input": "ikinci Pazar döneceğim",
    "Context": {
      "ReferenceDateTime": "2017-09-27T00:00:00"
    },
    "NotSupportedByDesign": "javascript,python,java",
    "Results": [
      {
        "Text": "ikinci Pazar",
        "Type": "date",
        "Value": {
          "Timex": "2017-09-10",
          "FutureResolution": {
            "date": "2017-09-10"
          },
          "PastResolution": {
            "date": "2017-09-10"
          }
        },
        "Start": 0,
        "Length": 12
      }
    ]
  },
  {
    "Input": "ilk Pazar döneceğim",
    "Context": {
      "ReferenceDateTime": "2017-09-27T00:00:00"
    },
    "NotSupportedByDesign": "javascript,python,java",
    "Results": [
      {
        "Text": "ilk Pazar",
        "Type": "date",
        "Value": {
          "Timex": "2017-09-03",
          "FutureResolution": {
            "date": "2017-09-03"
          },
          "PastResolution": {
            "date": "2017-09-03"
          }
        },
        "Start": 0,
        "Length": 9
      }
    ]
  },
  {
    "Input": "üçüncü Salı döneceğim",
    "Context": {
      "ReferenceDateTime": "2017-09-27T00:00:00"
    },
    "NotSupportedByDesign": "javascript,python,java",
    "Results": [
      {
        "Text": "üçüncü Salı",
        "Type": "date",
        "Value": {
          "Timex": "2017-09-19",
          "FutureResolution": {
            "date": "2017-09-19"
          },
          "PastResolution": {
            "date": "2017-09-19"
          }
        },
        "Start": 0,
        "Length": 11
      }
    ]
  },
  {
    "Input": "beşinci Pazar döneceğim",
    "Context": {
      "ReferenceDateTime": "2017-09-27T00:00:00"
    },
    "NotSupportedByDesign": "javascript,python,java",
    "Results": [
      {
        "Text": "beşinci Pazar",
        "Type": "date",
        "Value": {
          "Timex": "2017-09-31",
          "FutureResolution": {
            "date": "0001-01-01"
          },
          "PastResolution": {
            "date": "0001-01-01"
          }
        },
        "Start": 0,
        "Length": 13
      }
    ]
  },
  {
    "Input": "gelecek ayın 20'sinde döndüm",
    "Context": {
      "ReferenceDateTime": "2016-11-07T00:00:00"
    },
    "NotSupportedByDesign": "javascript,python,java",
    "Results": [
      {
        "Text": "gelecek ayın 20'si",
        "Type": "date",
        "Value": {
          "Timex": "2016-12-20",
          "FutureResolution": {
            "date": "2016-12-20"
          },
          "PastResolution": {
            "date": "2016-12-20"
          }
        },
        "Start": 0,
        "Length": 18
      }
    ]
  },
  {
    "Input": "Bu ayın 31'inde döndüm",
    "Context": {
      "ReferenceDateTime": "2016-11-07T00:00:00"
    },
    "NotSupportedByDesign": "javascript,python,java",
    "Results": [
      {
        "Text": "Bu ayın 31'i",
        "Type": "date",
        "Value": {
          "Timex": "2016-11-31",
          "FutureResolution": {
            "date": "0001-01-01"
          },
          "PastResolution": {
            "date": "0001-01-01"
          }
        },
        "Start": 0,
        "Length": 12
      }
    ]
  },
  {
    "Input": "12 Ocak 2018'de döneceğim",
    "Context": {
      "ReferenceDateTime": "2016-11-07T00:00:00"
    },
    "NotSupportedByDesign": "javascript,python,java",
    "Results": [
      {
        "Text": "12 Ocak 2018",
        "Type": "date",
        "Value": {
          "Timex": "2018-01-12",
          "FutureResolution": {
            "date": "2018-01-12"
          },
          "PastResolution": {
            "date": "2018-01-12"
          }
        },
        "Start": 0,
        "Length": 12
      }
    ]
  },
  {
    "Input": "18-09-2015'de döneceğim",
    "Context": {
      "ReferenceDateTime": "2016-11-07T00:00:00"
    },
    "NotSupportedByDesign": "javascript,python,java",
    "Results": [
      {
        "Text": "18-09-2015",
        "Type": "date",
        "Value": {
          "Timex": "2015-09-18",
          "FutureResolution": {
            "date": "2015-09-18"
          },
          "PastResolution": {
            "date": "2015-09-18"
          }
        },
        "Start": 0,
        "Length": 10
      }
    ]
  },
  {
    "Input": "iki gün önce döndüm",
    "Context": {
      "ReferenceDateTime": "2016-11-07T00:00:00"
    },
    "NotSupportedByDesign": "javascript,python,java",
    "Results": [
      {
        "Text": "iki gün önce",
        "Type": "date",
        "Value": {
          "Timex": "2016-11-05",
          "FutureResolution": {
            "date": "2016-11-05"
          },
          "PastResolution": {
            "date": "2016-11-05"
          }
        },
        "Start": 0,
        "Length": 12
      }
    ]
  },
  {
    "Input": "iki yıl önce döndüm",
    "Context": {
      "ReferenceDateTime": "2016-11-07T00:00:00"
    },
    "NotSupportedByDesign": "javascript,python,java",
    "Results": [
      {
        "Text": "iki yıl önce",
        "Type": "date",
        "Value": {
          "Timex": "2014-11-07",
          "FutureResolution": {
            "date": "2014-11-07"
          },
          "PastResolution": {
            "date": "2014-11-07"
          }
        },
        "Start": 0,
        "Length": 12
      }
    ]
  },
  {
    "Input": "16 Kasım 2016",
    "Context": {
      "ReferenceDateTime": "2016-11-14T00:00:00"
    },
    "NotSupportedByDesign": "javascript,python,java",
    "Results": [
      {
        "Text": "16 Kasım 2016",
        "Type": "date",
        "Value": {
          "Timex": "2016-11-16",
          "FutureResolution": {
            "date": "2016-11-16"
          },
          "PastResolution": {
            "date": "2016-11-16"
          }
        },
        "Start": 0,
        "Length": 13
      }
    ]
  },
  {
    "Input": "1 ay 21 gün önce bir toplantımız vardı",
    "Context": {
      "ReferenceDateTime": "2017-11-23T00:00:00"
    },
    "NotSupportedByDesign": "javascript,python,java",
    "Results": [
      {
        "Text": "1 ay 21 gün önce",
        "Type": "date",
        "Value": {
          "Timex": "2017-10-02",
          "FutureResolution": {
            "date": "2017-10-02"
          },
          "PastResolution": {
            "date": "2017-10-02"
          }
        },
        "Start": 0,
        "Length": 16
      }
    ]
  },
  {
    "Input": "2 yıl 1 ay 21 gün önce buradan ayrıldım",
    "Context": {
      "ReferenceDateTime": "2017-11-23T00:00:00"
    },
    "NotSupportedByDesign": "javascript,python,java",
    "Results": [
      {
        "Text": "2 yıl 1 ay 21 gün önce",
        "Type": "date",
        "Value": {
          "Timex": "2015-10-02",
          "FutureResolution": {
            "date": "2015-10-02"
          },
          "PastResolution": {
            "date": "2015-10-02"
          }
        },
        "Start": 0,
        "Length": 22
      }
    ]
  },
  {
    "Input": "2 yıl 21 gün sonra buradan ayrılacağım",
    "Context": {
      "ReferenceDateTime": "2017-11-23T00:00:00"
    },
    "NotSupportedByDesign": "javascript,python,java",
    "Results": [
      {
        "Text": "2 yıl 21 gün sonra",
        "Type": "date",
        "Value": {
          "Timex": "2019-12-14",
          "FutureResolution": {
            "date": "2019-12-14"
          },
          "PastResolution": {
            "date": "2019-12-14"
          }
        },
        "Start": 0,
        "Length": 18
      }
    ]
  },
  {
    "Input": "1 ay 2 yıl 21 gün önce buradan ayrıldım",
    "Context": {
      "ReferenceDateTime": "2017-11-23T00:00:00"
    },
    "NotSupportedByDesign": "javascript,python,java",
    "Results": [
      {
        "Text": "1 ay 2 yıl 21 gün önce",
        "Type": "date",
        "Value": {
          "Timex": "2015-10-02",
          "FutureResolution": {
            "date": "2015-10-02"
          },
          "PastResolution": {
            "date": "2015-10-02"
          }
        },
        "Start": 0,
        "Length": 22
      }
    ]
  },
  {
    "Input": "1 ay, 21 gün önce bir toplantımız vardı",
    "Context": {
      "ReferenceDateTime": "2017-11-23T00:00:00"
    },
    "NotSupportedByDesign": "javascript,python,java",
    "Results": [
      {
        "Text": "1 ay, 21 gün önce",
        "Type": "date",
        "Value": {
          "Timex": "2017-10-02",
          "FutureResolution": {
            "date": "2017-10-02"
          },
          "PastResolution": {
            "date": "2017-10-02"
          }
        },
        "Start": 0,
        "Length": 17
      }
    ]
  },
  {
    "Input": "Gelecek ayın 20'sinde bir toplantımız vardı",
    "Context": {
      "ReferenceDateTime": "2017-12-07T00:00:00"
    },
    "NotSupportedByDesign": "javascript,python,java",
    "Results": [
      {
        "Text": "Gelecek ayın 20'si",
        "Type": "date",
        "Value": {
          "Timex": "2018-01-20",
          "FutureResolution": {
            "date": "2018-01-20"
          },
          "PastResolution": {
            "date": "2018-01-20"
          }
        },
        "Start": 0,
        "Length": 18
      }
    ]
  },
  {
    "Input": "5 Aralık 1391'de bir toplantımız vardı",
    "Context": {
      "ReferenceDateTime": "2017-12-18T00:00:00"
    },
    "NotSupportedByDesign": "javascript,python,java",
    "Results": [
      {
        "Text": "5 Aralık 1391",
        "Type": "date",
        "Value": {
          "Timex": "1391-12-05",
          "FutureResolution": {
            "date": "1391-12-05"
          },
          "PastResolution": {
            "date": "1391-12-05"
          }
        },
        "Start": 0,
        "Length": 13
      }
    ]
  },
  {
    "Input": "yirmi iki Ocak 2018, Pazartesi",
    "Context": {
      "ReferenceDateTime": "2016-11-07T00:00:00"
    },
    "NotSupportedByDesign": "javascript,python,java",
    "Results": [
      {
        "Text": "yirmi iki Ocak 2018, Pazartesi",
        "Type": "date",
        "Value": {
          "Timex": "2018-01-22",
          "FutureResolution": {
            "date": "2018-01-22"
          },
          "PastResolution": {
            "date": "2018-01-22"
          }
        },
        "Start": 0,
        "Length": 30
      }
    ]
  },
  {
    "Input": "Yirmi bir Ocak iki bin on sekiz, Pazar günü",
    "Context": {
      "ReferenceDateTime": "2016-11-07T00:00:00"
    },
    "NotSupportedByDesign": "javascript,python,java",
    "Results": [
      {
        "Text": "Yirmi bir Ocak iki bin on sekiz, Pazar günü",
        "Type": "date",
        "Value": {
          "Timex": "2018-01-21",
          "FutureResolution": {
            "date": "2018-01-21"
          },
          "PastResolution": {
            "date": "2018-01-21"
          }
        },
        "Start": 0,
        "Length": 43
      }
    ]
  },
  {
    "Input": "yirmi bir Eylül bin dokuz yüz yetmiş sekiz",
    "Context": {
      "ReferenceDateTime": "2016-11-07T00:00:00"
    },
    "NotSupportedByDesign": "javascript,python,java",
    "Results": [
      {
        "Text": "yirmi bir Eylül bin dokuz yüz yetmiş sekiz",
        "Type": "date",
        "Value": {
          "Timex": "1978-09-21",
          "FutureResolution": {
            "date": "1978-09-21"
          },
          "PastResolution": {
            "date": "1978-09-21"
          }
        },
        "Start": 0,
        "Length": 42
      }
    ]
  },
  {
    "Input": "10 Eylül bin dokuz yüz bir",
    "Context": {
      "ReferenceDateTime": "2016-11-07T00:00:00"
    },
    "NotSupportedByDesign": "javascript,python,java",
    "Results": [
      {
        "Text": "10 Eylül bin dokuz yüz bir",
        "Type": "date",
        "Value": {
          "Timex": "1901-09-10",
          "FutureResolution": {
            "date": "1901-09-10"
          },
          "PastResolution": {
            "date": "1901-09-10"
          }
        },
        "Start": 0,
        "Length": 26
      }
    ]
  },
  {
    "Input": "iki bin yılı Eylül'ün onunda",
    "Context": {
      "ReferenceDateTime": "2016-11-07T00:00:00"
    },
    "NotSupportedByDesign": "javascript,python,java",
    "Results": [
      {
        "Text": "iki bin yılı Eylül'ün onu",
        "Type": "date",
        "Value": {
          "Timex": "2000-09-10",
          "FutureResolution": {
            "date": "2000-09-10"
          },
          "PastResolution": {
            "date": "2000-09-10"
          }
        },
        "Start": 0,
        "Length": 25
      }
    ]
  },
  {
    "Input": "Gelecek ayın ilk Cuması seni göreceğim",
    "Context": {
      "ReferenceDateTime": "2018-03-20T09:58:00"
    },
    "NotSupportedByDesign": "javascript,python,java",
    "Results": [
      {
        "Text": "Gelecek ayın ilk Cuması",
        "Type": "date",
        "Value": {
          "Timex": "XXXX-04-WXX-5-#1",
          "FutureResolution": {
            "date": "2018-04-06"
          },
          "PastResolution": {
            "date": "2018-04-06"
          }
        },
        "Start": 0,
        "Length": 23
      }
    ]
  },
  {
    "Input": "Peki, gelecek ayın ikinci pazartesi yapalım mı?",
    "Context": {
      "ReferenceDateTime": "2018-03-20T10:45:00"
    },
    "NotSupportedByDesign": "javascript,python,java",
    "Results": [
      {
        "Text": "gelecek ayın ikinci pazartesi",
        "Type": "date",
        "Value": {
          "Timex": "XXXX-04-WXX-1-#2",
          "FutureResolution": {
            "date": "2018-04-09"
          },
          "PastResolution": {
            "date": "2018-04-09"
          }
        },
        "Start": 6,
        "Length": 29
      }
    ]
  },
  {
    "Input": "Önceki ayın üçüncü Çarşambası döndüm",
    "Context": {
      "ReferenceDateTime": "2018-03-20T10:45:00"
    },
    "NotSupportedByDesign": "javascript,python,java",
    "Results": [
      {
        "Text": "Önceki ayın üçüncü Çarşambası",
        "Type": "date",
        "Value": {
          "Timex": "XXXX-02-WXX-3-#3",
          "FutureResolution": {
            "date": "2018-02-21"
          },
          "PastResolution": {
            "date": "2018-02-21"
          }
        },
        "Start": 0,
        "Length": 29
      }
    ]
  },
  {
    "Input": "Gelecek hafta Salı seyahat edeceğim",
    "Context": {
      "ReferenceDateTime": "2018-03-20T22:16:00"
    },
    "NotSupportedByDesign": "javascript,python,java",
    "Results": [
      {
        "Text": "Gelecek hafta Salı",
        "Type": "date",
        "Value": {
          "Timex": "2018-03-27",
          "FutureResolution": {
            "date": "2018-03-27"
          },
          "PastResolution": {
            "date": "2018-03-27"
          }
        },
        "Start": 0,
        "Length": 18
      }
    ]
  },
  {
    "Input": "Gelecek hafta Pazar günü ödevi hallet",
    "Context": {
      "ReferenceDateTime": "2018-03-20T22:16:00"
    },
    "NotSupportedByDesign": "javascript,python,java",
    "Results": [
      {
        "Text": "Gelecek hafta Pazar günü",
        "Type": "date",
        "Value": {
          "Timex": "2018-04-01",
          "FutureResolution": {
            "date": "2018-04-01"
          },
          "PastResolution": {
            "date": "2018-04-01"
          }
        },
        "Start": 0,
        "Length": 24
      }
    ]
  },
  {
    "Input": "Yarından itibaren iki gün içinde döneceğim",
    "Context": {
      "ReferenceDateTime": "2018-04-20T00:00:00"
    },
    "NotSupportedByDesign": "javascript,python,java",
    "Results": [
      {
        "Text": "Yarından itibaren iki gün içinde",
        "Type": "date",
        "Value": {
          "Timex": "2018-04-23",
          "FutureResolution": {
            "date": "2018-04-23"
          },
          "PastResolution": {
            "date": "2018-04-23"
          }
        },
        "Start": 0,
        "Length": 32
      }
    ]
  },
  {
    "Input": "Dünden itibaren dört gün içinde döneceğim",
    "Context": {
      "ReferenceDateTime": "2018-04-20T00:00:00"
    },
    "NotSupportedByDesign": "javascript,python,java",
    "Results": [
      {
        "Text": "Dünden itibaren dört gün içinde",
        "Type": "date",
        "Value": {
          "Timex": "2018-04-23",
          "FutureResolution": {
            "date": "2018-04-23"
          },
          "PastResolution": {
            "date": "2018-04-23"
          }
        },
        "Start": 0,
        "Length": 31
      }
    ]
  },
  {
    "Input": "13.5.2015'de boş musun?",
    "Context": {
      "ReferenceDateTime": "2017-03-22T00:00:00"
    },
    "NotSupportedByDesign": "javascript,python,java",
    "Results": [
      {
        "Text": "13.5.2015",
        "Type": "date",
        "Value": {
          "Timex": "2015-05-13",
          "FutureResolution": {
            "date": "2015-05-13"
          },
          "PastResolution": {
            "date": "2015-05-13"
          }
        },
        "Start": 0,
        "Length": 9
      }
    ]
  },
  {
    "Input": "13.05.2015'de uygun musun?",
    "Context": {
      "ReferenceDateTime": "2017-03-22T00:00:00"
    },
    "NotSupportedByDesign": "javascript,python,java",
    "Results": [
      {
        "Text": "13.05.2015",
        "Type": "date",
        "Value": {
          "Timex": "2015-05-13",
          "FutureResolution": {
            "date": "2015-05-13"
          },
          "PastResolution": {
            "date": "2015-05-13"
          }
        },
        "Start": 0,
        "Length": 10
      }
    ]
  },
  {
    "Input": "07.03.2017'de döneceğim",
    "Context": {
      "ReferenceDateTime": "2016-11-07T00:00:00"
    },
    "NotSupportedByDesign": "javascript,python,java",
    "Results": [
      {
        "Text": "07.03.2017",
        "Type": "date",
        "Value": {
          "Timex": "2017-03-07",
          "FutureResolution": {
            "date": "2017-03-07"
          },
          "PastResolution": {
            "date": "2017-03-07"
          }
        },
        "Start": 0,
        "Length": 10
      }
    ]
  },
  {
    "Input": "05/05/1989'da döneceğim",
    "Context": {
      "ReferenceDateTime": "2016-11-07T00:00:00"
    },
    "NotSupportedByDesign": "javascript,python,java",
    "Results": [
      {
        "Text": "05/05/1989",
        "Type": "date",
        "Value": {
          "Timex": "1989-05-05",
          "FutureResolution": {
            "date": "1989-05-05"
          },
          "PastResolution": {
            "date": "1989-05-05"
          }
        },
        "Start": 0,
        "Length": 10
      }
    ]
  },
  {
    "Input": "05/05/1971'de döneceğim",
    "Context": {
      "ReferenceDateTime": "2016-11-07T00:00:00"
    },
    "NotSupportedByDesign": "javascript,python,java",
    "Results": [
      {
        "Text": "05/05/1971",
        "Type": "date",
        "Value": {
          "Timex": "1971-05-05",
          "FutureResolution": {
            "date": "1971-05-05"
          },
          "PastResolution": {
            "date": "1971-05-05"
          }
        },
        "Start": 0,
        "Length": 10
      }
    ]
  },
  {
    "Input": "Şu andan itibaren iki Pazar sonra uygun musun?",
    "Context": {
      "ReferenceDateTime": "2018-05-07T00:00:00"
    },
    "NotSupportedByDesign": "javascript,python,java",
    "Results": [
      {
        "Text": "Şu andan itibaren iki Pazar sonra",
        "Type": "date",
        "Value": {
          "Timex": "2018-05-20",
          "FutureResolution": {
            "date": "2018-05-20"
          },
          "PastResolution": {
            "date": "2018-05-20"
          }
        },
        "Start": 0,
        "Length": 33
      }
    ]
  },
  {
    "Input": "iki Pazartesi sonra uygun musun?",
    "Context": {
      "ReferenceDateTime": "2018-05-07T00:00:00"
    },
    "NotSupportedByDesign": "javascript,python,java",
    "Results": [
      {
        "Text": "iki Pazartesi sonra",
        "Type": "date",
        "Value": {
          "Timex": "2018-05-21",
          "FutureResolution": {
            "date": "2018-05-21"
          },
          "PastResolution": {
            "date": "2018-05-21"
          }
        },
        "Start": 0,
        "Length": 19
      }
    ]
  },
  {
    "Input": "Bugünden iki gün sonra uygun musun?",
    "Context": {
      "ReferenceDateTime": "2018-05-31T00:00:00"
    },
    "NotSupportedByDesign": "javascript,python,java",
    "Results": [
      {
        "Text": "Bugünden iki gün sonra",
        "Type": "date",
        "Value": {
          "Timex": "2018-06-02",
          "FutureResolution": {
            "date": "2018-06-02"
          },
          "PastResolution": {
            "date": "2018-06-02"
          }
        },
        "Start": 0,
        "Length": 22
      }
    ]
  },
  {
    "Input": "Yarından itibaren üç hafta sonra uygun musun?",
    "Context": {
      "ReferenceDateTime": "2018-05-31T00:00:00"
    },
    "NotSupportedByDesign": "javascript,python,java",
    "Results": [
      {
        "Text": "Yarından itibaren üç hafta sonra",
        "Type": "date",
        "Value": {
          "Timex": "2018-06-22",
          "FutureResolution": {
            "date": "2018-06-22"
          },
          "PastResolution": {
            "date": "2018-06-22"
          }
        },
        "Start": 0,
        "Length": 32
      }
    ]
  },
  {
    "Input": "Dünden iki gün önce neredeydin?",
    "Context": {
      "ReferenceDateTime": "2018-05-31T00:00:00"
    },
    "NotSupportedByDesign": "javascript,python,java",
    "Results": [
      {
        "Text": "Dünden iki gün önce",
        "Type": "date",
        "Value": {
          "Timex": "2018-05-28",
          "FutureResolution": {
            "date": "2018-05-28"
          },
          "PastResolution": {
            "date": "2018-05-28"
          }
        },
        "Start": 0,
        "Length": 19
      }
    ]
  },
  {
    "Input": "3 hafta içinde ayrılacağım",
    "Context": {
      "ReferenceDateTime": "2018-07-05T00:00:00"
    },
    "NotSupportedByDesign": "javascript,python,java",
    "Results": [
      {
        "Text": "3 hafta içinde",
        "Type": "date",
        "Value": {
          "Timex": "2018-07-26",
          "FutureResolution": {
            "date": "2018-07-26"
          },
          "PastResolution": {
            "date": "2018-07-26"
          }
        },
        "Start": 0,
        "Length": 14
      }
    ]
  },
  {
    "Input": "Cortana, lütfen dört iş günü içinde bir-ara bir Skype görüşmesi ayarla",
    "Context": {
      "ReferenceDateTime": "2018-08-21T08:00:00"
    },
    "NotSupportedByDesign": "javascript,python,java",
    "Results": [
      {
        "Text": "dört iş günü içinde",
        "Type": "date",
        "Value": {
          "Timex": "2018-08-27",
          "FutureResolution": {
            "date": "2018-08-27"
          },
          "PastResolution": {
            "date": "2018-08-27"
          }
        },
        "Start": 16,
        "Length": 19
      }
    ]
  },
  {
    "Input": "Bugünkü derse gelmedi",
    "Comment": "DateTime V2 enhancements",
    "Context": {
      "ReferenceDateTime": "2019-09-23T00:00:00"
    },
    "NotSupportedByDesign": "javascript,python,java",
    "Results": [
      {
        "Text": "Bugünkü",
        "Type": "date",
        "Value": {
          "Timex": "2019-09-23",
          "FutureResolution": {
            "date": "2019-09-23"
          },
          "PastResolution": {
            "date": "2019-09-23"
          }
        },
        "Start": 0,
        "Length": 7
      }
    ]
  },
  {
    "Input": "Dünkü derse gelmedi",
    "Comment": "DateTime V2 enhancements",
    "Context": {
      "ReferenceDateTime": "2019-09-23T00:00:00"
    },
    "NotSupportedByDesign": "javascript,python,java",
    "Results": [
      {
        "Text": "dünkü",
        "Type": "date",
        "Value": {
          "Timex": "2019-09-22",
          "FutureResolution": {
            "date": "2019-09-22"
          },
          "PastResolution": {
            "date": "2019-09-22"
          }
        },
        "Start": 0,
        "Length": 5
      }
    ]
  }
]